github_repo_traffic/__init__.py
github_repo_traffic/data.py
github_repo_traffic/readme.py
github_repo_traffic-2.1.1.dist-info/LICENSE
github_repo_traffic-2.1.1.dist-info/METADATA
github_repo_traffic-2.1.1.dist-info/WHEEL
github_repo_traffic-2.1.1.dist-info/entry_points.txt
github_repo_traffic-2.1.1.dist-info/RECORD
