Metadata-Version: 2.1
Name: github_repo_traffic
Version: 2.1.1
Summary: 
Author: Will Humphlett
Author-email: will@humphlett.net
Requires-Python: >=3.10,<4.0
Classifier: Programming Language :: Python :: 3
Classifier: Programming Language :: Python :: 3.10
Classifier: Programming Language :: Python :: 3.11
Classifier: Programming Language :: Python :: 3.12
Requires-Dist: PyGithub (>=1.55,<2.0)
Requires-Dist: asciichartpy (>=1.5.25,<2.0.0)
Requires-Dist: numpy (>=1,<2)
Requires-Dist: pandas (>=1.4.3,<2.0.0)
Requires-Dist: python-dotenv (>=0.20.0,<0.21.0)
